src/__init__.py
src/update_hostgrp_poc.py
update_hostgrp_poc-0.2.2.dist-info/LICENSE
update_hostgrp_poc-0.2.2.dist-info/METADATA
update_hostgrp_poc-0.2.2.dist-info/WHEEL
update_hostgrp_poc-0.2.2.dist-info/entry_points.txt
update_hostgrp_poc-0.2.2.dist-info/top_level.txt
update_hostgrp_poc-0.2.2.dist-info/zip-safe
update_hostgrp_poc-0.2.2.dist-info/RECORD
